colony_print/__init__.py
colony_print/__main__.py
colony_print/main.py
colony_print/node.py
colony_print/controllers/__init__.py
colony_print/controllers/base.py
colony_print/controllers/document.py
colony_print/controllers/job.py
colony_print/controllers/node.py
colony_print/controllers/printer.py
colony_print/printing/__init__.py
colony_print/printing/binie/__init__.py
colony_print/printing/binie/exceptions.py
colony_print/printing/binie/system.py
colony_print/printing/binie/visitor.py
colony_print/printing/common/__init__.py
colony_print/printing/common/base.py
colony_print/printing/manager/__init__.py
colony_print/printing/manager/ast.py
colony_print/printing/manager/exceptions.py
colony_print/printing/manager/parser.py
colony_print/printing/manager/system.py
colony_print/printing/manager/visitor.py
colony_print/printing/pdf/__init__.py
colony_print/printing/pdf/exceptions.py
colony_print/printing/pdf/system.py
colony_print/printing/pdf/visitor.py
colony_print/static/example/print.html
colony_print/static/example/js/main.js
colony_print/static/example/xml/hello.xml
colony_print/static/example/xml/money_sale_slip.xml
colony_print-0.4.8.dist-info/METADATA
colony_print-0.4.8.dist-info/WHEEL
colony_print-0.4.8.dist-info/top_level.txt
colony_print-0.4.8.dist-info/RECORD
